README.md
setup.py
SOPRANOS/SOPRANOS_fun.py
SOPRANOS/__init__.py
SOPRANOS/black_body_flux_density.py
SOPRANOS/calc_black_body_flux_filters.py
SOPRANOS/class_chi2.py
SOPRANOS/constant.py
SOPRANOS/cosmo_pars.py
SOPRANOS/distances_conversions.py
SOPRANOS/energy_conversions.py
SOPRANOS/extinction.py
SOPRANOS/find.py
SOPRANOS/get_filter.py
SOPRANOS/lum_dist.py
SOPRANOS/read_data_from_file.py
SOPRANOS/sn_cooling_sw.py
SOPRANOS.egg-info/PKG-INFO
SOPRANOS.egg-info/SOURCES.txt
SOPRANOS.egg-info/dependency_links.txt
SOPRANOS.egg-info/requires.txt
SOPRANOS.egg-info/top_level.txt