Metadata-Version: 1.2
Name: SOPRANOS
Version: 0.0.18
Summary: development version
Home-page: UNKNOWN
Author: Maayane T. Soumagnac, Noam Ganot, Ido Irani, Erez Zimmerman
Author-email: maayane.soumagnac@weizmann.ac.il
License: UNKNOWN
Keywords: astronomy
Platform: UNKNOWN
Requires-Python: >=3
